{"23":[{"X":440,"Y":390,"gridNum":0},{"X":487,"Y":408,"gridNum":0},{"X":487,"Y":415,"gridNum":0},{"X":594,"Y":450,"gridNum":0},{"X":622,"Y":470,"gridNum":0},{"X":607,"Y":493,"gridNum":0},{"X":651,"Y":526,"gridNum":0},{"X":671,"Y":538,"gridNum":0},{"X":722,"Y":487,"gridNum":0},{"X":723,"Y":435,"gridNum":0},{"X":646,"Y":432,"gridNum":0},{"X":644,"Y":449,"gridNum":0},{"X":653,"Y":452,"gridNum":0},{"X":651,"Y":526,"gridNum":0},{"X":627,"Y":550,"gridNum":0},{"X":627,"Y":561,"gridNum":0},{"X":645,"Y":577,"gridNum":0},{"X":670,"Y":563,"gridNum":0},{"X":803,"Y":670,"gridNum":0},{"X":847,"Y":680,"gridNum":0},{"X":980,"Y":669,"gridNum":0},{"X":988,"Y":658,"gridNum":0},{"X":988,"Y":644,"gridNum":0},{"X":995,"Y":636,"gridNum":0},{"X":988,"Y":615,"gridNum":0},{"X":1012,"Y":599,"gridNum":0},{"X":1033,"Y":645,"gridNum":0},{"X":1154,"Y":626,"gridNum":0},{"X":1195,"Y":713,"gridNum":0},{"X":1230,"Y":723,"gridNum":0},{"X":1277,"Y":685,"gridNum":0},{"X":1330,"Y":755,"gridNum":0},{"X":1365,"Y":730,"gridNum":0},{"X":1430,"Y":681,"gridNum":0},{"X":1435,"Y":665,"gridNum":0},{"X":1427,"Y":650,"gridNum":0},{"X":1428,"Y":629,"gridNum":0},{"X":1414,"Y":613,"gridNum":0},{"X":1346,"Y":517,"gridNum":0},{"X":1332,"Y":495,"gridNum":0},{"X":1350,"Y":494,"gridNum":0},{"X":1352,"Y":451,"gridNum":0},{"X":1426,"Y":455,"gridNum":0}],"7":[{"X":1104,"Y":541,"gridNum":0},{"X":1092,"Y":542,"gridNum":0},{"X":1009,"Y":577,"gridNum":0},{"X":1012,"Y":599,"gridNum":0},{"X":1033,"Y":645,"gridNum":0},{"X":1154,"Y":626,"gridNum":0},{"X":1195,"Y":713,"gridNum":0},{"X":1230,"Y":723,"gridNum":0},{"X":1277,"Y":685,"gridNum":0},{"X":1330,"Y":755,"gridNum":0},{"X":1365,"Y":730,"gridNum":0},{"X":1430,"Y":681,"gridNum":0},{"X":1435,"Y":665,"gridNum":0},{"X":1427,"Y":650,"gridNum":0},{"X":1428,"Y":629,"gridNum":0},{"X":1414,"Y":613,"gridNum":0},{"X":1372,"Y":551,"gridNum":0},{"X":1420,"Y":518,"gridNum":0},{"X":1392,"Y":482,"gridNum":0},{"X":1346,"Y":517,"gridNum":0},{"X":1332,"Y":495,"gridNum":0},{"X":1246,"Y":492,"gridNum":0},{"X":1249,"Y":391,"gridNum":0},{"X":1303,"Y":391,"gridNum":0},{"X":1318,"Y":403,"gridNum":0},{"X":1372,"Y":369,"gridNum":0},{"X":1390,"Y":382,"gridNum":0}],"62":[{"X":1426,"Y":455,"gridNum":0},{"X":1352,"Y":451,"gridNum":0},{"X":1350,"Y":494,"gridNum":0},{"X":1332,"Y":495,"gridNum":0},{"X":1346,"Y":517,"gridNum":0},{"X":1372,"Y":551,"gridNum":0},{"X":1407,"Y":597,"gridNum":0},{"X":1414,"Y":613,"gridNum":0},{"X":1428,"Y":629,"gridNum":0},{"X":1427,"Y":650,"gridNum":0},{"X":1435,"Y":665,"gridNum":0},{"X":1430,"Y":681,"gridNum":0},{"X":1365,"Y":730,"gridNum":0},{"X":1330,"Y":755,"gridNum":0},{"X":1277,"Y":685,"gridNum":0},{"X":1230,"Y":723,"gridNum":0},{"X":1195,"Y":713,"gridNum":0},{"X":1154,"Y":626,"gridNum":0},{"X":1033,"Y":645,"gridNum":0},{"X":1012,"Y":599,"gridNum":0},{"X":1009,"Y":577,"gridNum":0},{"X":1092,"Y":542,"gridNum":0},{"X":1104,"Y":541,"gridNum":0},{"X":1189,"Y":490,"gridNum":0},{"X":1246,"Y":492,"gridNum":0},{"X":1332,"Y":495,"gridNum":0},{"X":1350,"Y":494,"gridNum":0},{"X":1352,"Y":451,"gridNum":0},{"X":1426,"Y":455,"gridNum":0}],"36":[{"X":1104,"Y":541,"gridNum":0},{"X":1092,"Y":542,"gridNum":0},{"X":1009,"Y":577,"gridNum":0},{"X":1012,"Y":599,"gridNum":0},{"X":1033,"Y":645,"gridNum":0},{"X":1154,"Y":626,"gridNum":0},{"X":1215,"Y":511,"gridNum":0},{"X":1218,"Y":490,"gridNum":0},{"X":1226,"Y":226,"gridNum":0},{"X":1193,"Y":162,"gridNum":0},{"X":1207,"Y":0,"gridNum":0}],"20":[{"X":1561,"Y":369,"gridNum":0},{"X":1424,"Y":360,"gridNum":0},{"X":1390,"Y":382,"gridNum":0},{"X":1329,"Y":419,"gridNum":0},{"X":1318,"Y":402,"gridNum":0},{"X":1303,"Y":391,"gridNum":0},{"X":1249,"Y":391,"gridNum":0},{"X":1246,"Y":492,"gridNum":0},{"X":1218,"Y":490,"gridNum":0},{"X":1189,"Y":490,"gridNum":0},{"X":1104,"Y":541,"gridNum":0},{"X":1092,"Y":542,"gridNum":0},{"X":1009,"Y":577,"gridNum":0},{"X":1012,"Y":599,"gridNum":0},{"X":988,"Y":615,"gridNum":0},{"X":995,"Y":636,"gridNum":0},{"X":988,"Y":644,"gridNum":0},{"X":988,"Y":658,"gridNum":0},{"X":980,"Y":669,"gridNum":0},{"X":847,"Y":680,"gridNum":0},{"X":803,"Y":670,"gridNum":0},{"X":670,"Y":563,"gridNum":0},{"X":645,"Y":577,"gridNum":0},{"X":627,"Y":561,"gridNum":0},{"X":627,"Y":550,"gridNum":0},{"X":651,"Y":526,"gridNum":0},{"X":607,"Y":493,"gridNum":0},{"X":622,"Y":470,"gridNum":0},{"X":644,"Y":449,"gridNum":0},{"X":646,"Y":432,"gridNum":0},{"X":723,"Y":435,"gridNum":0},{"X":724,"Y":363,"gridNum":0},{"X":726,"Y":119,"gridNum":0},{"X":723,"Y":104,"gridNum":0},{"X":641,"Y":4,"gridNum":0}]}