<?xml version="1.0"?>
<ArrayOfVertex xmlns:xsi="http://www.w3.org/2001/XMLSchema-instance" xmlns:xsd="http://www.w3.org/2001/XMLSchema">
  <Vertex>
    <gridNum>0</gridNum>
    <x>330</x>
    <y>387</y>
  </Vertex>
  <Vertex>
    <gridNum>0</gridNum>
    <x>344</x>
    <y>381</y>
  </Vertex>
  <Vertex>
    <gridNum>0</gridNum>
    <x>315</x>
    <y>340</y>
  </Vertex>
  <Vertex>
    <gridNum>0</gridNum>
    <x>300</x>
    <y>350</y>
  </Vertex>
  <Vertex>
    <gridNum>0</gridNum>
    <x>304</x>
    <y>361</y>
  </Vertex>
  <Vertex>
    <gridNum>0</gridNum>
    <x>279</x>
    <y>418</y>
  </Vertex>
  <Vertex>
    <gridNum>0</gridNum>
    <x>231</x>
    <y>468</y>
  </Vertex>
  <Vertex>
    <gridNum>0</gridNum>
    <x>201</x>
    <y>498</y>
  </Vertex>
  <Vertex>
    <gridNum>0</gridNum>
    <x>282</x>
    <y>368</y>
  </Vertex>
  <Vertex>
    <gridNum>0</gridNum>
    <x>237</x>
    <y>435</y>
  </Vertex>
  <Vertex>
    <gridNum>0</gridNum>
    <x>206</x>
    <y>479</y>
  </Vertex>
  <Vertex>
    <gridNum>0</gridNum>
    <x>173</x>
    <y>552</y>
  </Vertex>
  <Vertex>
    <gridNum>0</gridNum>
    <x>158</x>
    <y>584</y>
  </Vertex>
  <Vertex>
    <gridNum>0</gridNum>
    <x>262</x>
    <y>635</y>
  </Vertex>
  <Vertex>
    <gridNum>0</gridNum>
    <x>287</x>
    <y>591</y>
  </Vertex>
  <Vertex>
    <gridNum>0</gridNum>
    <x>313</x>
    <y>562</y>
  </Vertex>
  <Vertex>
    <gridNum>0</gridNum>
    <x>416</x>
    <y>480</y>
  </Vertex>
  <Vertex>
    <gridNum>0</gridNum>
    <x>410</x>
    <y>468</y>
  </Vertex>
  <Vertex>
    <gridNum>0</gridNum>
    <x>493</x>
    <y>409</y>
  </Vertex>
  <Vertex>
    <gridNum>0</gridNum>
    <x>600</x>
    <y>334</y>
  </Vertex>
  <Vertex>
    <gridNum>0</gridNum>
    <x>669</x>
    <y>263</y>
  </Vertex>
  <Vertex>
    <gridNum>0</gridNum>
    <x>705</x>
    <y>230</y>
  </Vertex>
  <Vertex>
    <gridNum>0</gridNum>
    <x>712</x>
    <y>226</y>
  </Vertex>
  <Vertex>
    <gridNum>0</gridNum>
    <x>605</x>
    <y>116</y>
  </Vertex>
  <Vertex>
    <gridNum>0</gridNum>
    <x>441</x>
    <y>242</y>
  </Vertex>
  <Vertex>
    <gridNum>0</gridNum>
    <x>392</x>
    <y>184</y>
  </Vertex>
  <Vertex>
    <gridNum>0</gridNum>
    <x>271</x>
    <y>285</y>
  </Vertex>
  <Vertex>
    <gridNum>0</gridNum>
    <x>466</x>
    <y>122</y>
  </Vertex>
  <Vertex>
    <gridNum>0</gridNum>
    <x>260</x>
    <y>114</y>
  </Vertex>
  <Vertex>
    <gridNum>0</gridNum>
    <x>192</x>
    <y>183</y>
  </Vertex>
  <Vertex>
    <gridNum>0</gridNum>
    <x>106</x>
    <y>258</y>
  </Vertex>
  <Vertex>
    <gridNum>0</gridNum>
    <x>578</x>
    <y>513</y>
  </Vertex>
  <Vertex>
    <gridNum>0</gridNum>
    <x>493</x>
    <y>581</y>
  </Vertex>
  <Vertex>
    <gridNum>0</gridNum>
    <x>439</x>
    <y>627</y>
  </Vertex>
  <Vertex>
    <gridNum>0</gridNum>
    <x>340</x>
    <y>540</y>
  </Vertex>
  <Vertex>
    <gridNum>0</gridNum>
    <x>535</x>
    <y>643</y>
  </Vertex>
  <Vertex>
    <gridNum>0</gridNum>
    <x>475</x>
    <y>692</y>
  </Vertex>
  <Vertex>
    <gridNum>0</gridNum>
    <x>402</x>
    <y>655</y>
  </Vertex>
  <Vertex>
    <gridNum>0</gridNum>
    <x>624</x>
    <y>569</y>
  </Vertex>
  <Vertex>
    <gridNum>0</gridNum>
    <x>624</x>
    <y>476</y>
  </Vertex>
  <Vertex>
    <gridNum>0</gridNum>
    <x>670</x>
    <y>531</y>
  </Vertex>
  <Vertex>
    <gridNum>0</gridNum>
    <x>839</x>
    <y>393</y>
  </Vertex>
  <Vertex>
    <gridNum>0</gridNum>
    <x>886</x>
    <y>430</y>
  </Vertex>
  <Vertex>
    <gridNum>0</gridNum>
    <x>758</x>
    <y>599</y>
  </Vertex>
  <Vertex>
    <gridNum>0</gridNum>
    <x>699</x>
    <y>675</y>
  </Vertex>
  <Vertex>
    <gridNum>0</gridNum>
    <x>779</x>
    <y>617</y>
  </Vertex>
  <Vertex>
    <gridNum>0</gridNum>
    <x>864</x>
    <y>680</y>
  </Vertex>
  <Vertex>
    <gridNum>0</gridNum>
    <x>950</x>
    <y>571</y>
  </Vertex>
  <Vertex>
    <gridNum>0</gridNum>
    <x>866</x>
    <y>506</y>
  </Vertex>
  <Vertex>
    <gridNum>0</gridNum>
    <x>1012</x>
    <y>312</y>
  </Vertex>
  <Vertex>
    <gridNum>0</gridNum>
    <x>1077</x>
    <y>345</y>
  </Vertex>
  <Vertex>
    <gridNum>0</gridNum>
    <x>1125</x>
    <y>374</y>
  </Vertex>
  <Vertex>
    <gridNum>0</gridNum>
    <x>1166</x>
    <y>378</y>
  </Vertex>
  <Vertex>
    <gridNum>0</gridNum>
    <x>1218</x>
    <y>412</y>
  </Vertex>
  <Vertex>
    <gridNum>0</gridNum>
    <x>942</x>
    <y>352</y>
  </Vertex>
  <Vertex>
    <gridNum>0</gridNum>
    <x>922</x>
    <y>320</y>
  </Vertex>
  <Vertex>
    <gridNum>0</gridNum>
    <x>1184</x>
    <y>148</y>
  </Vertex>
  <Vertex>
    <gridNum>0</gridNum>
    <x>1165</x>
    <y>160</y>
  </Vertex>
  <Vertex>
    <gridNum>0</gridNum>
    <x>1129</x>
    <y>107</y>
  </Vertex>
  <Vertex>
    <gridNum>0</gridNum>
    <x>888</x>
    <y>263</y>
  </Vertex>
  <Vertex>
    <gridNum>0</gridNum>
    <x>858</x>
    <y>137</y>
  </Vertex>
  <Vertex>
    <gridNum>0</gridNum>
    <x>852</x>
    <y>133</y>
  </Vertex>
  <Vertex>
    <gridNum>0</gridNum>
    <x>1036</x>
    <y>168</y>
  </Vertex>
  <Vertex>
    <gridNum>0</gridNum>
    <x>1014</x>
    <y>60</y>
  </Vertex>
  <Vertex>
    <gridNum>0</gridNum>
    <x>1022</x>
    <y>97</y>
  </Vertex>
  <Vertex>
    <gridNum>0</gridNum>
    <x>792</x>
    <y>37</y>
  </Vertex>
  <Vertex>
    <gridNum>0</gridNum>
    <x>671</x>
    <y>66</y>
  </Vertex>
  <Vertex>
    <gridNum>0</gridNum>
    <x>720</x>
    <y>115</y>
  </Vertex>
  <Vertex>
    <gridNum>0</gridNum>
    <x>664</x>
    <y>180</y>
  </Vertex>
  <Vertex>
    <gridNum>0</gridNum>
    <x>322</x>
    <y>156</y>
  </Vertex>
  <Vertex>
    <gridNum>0</gridNum>
    <x>495</x>
    <y>321</y>
  </Vertex>
  <Vertex>
    <gridNum>0</gridNum>
    <x>555</x>
    <y>285</y>
  </Vertex>
  <Vertex>
    <gridNum>0</gridNum>
    <x>1070</x>
    <y>663</y>
  </Vertex>
  <Vertex>
    <gridNum>0</gridNum>
    <x>450</x>
    <y>733</y>
  </Vertex>
  <Vertex>
    <gridNum>0</gridNum>
    <x>381</x>
    <y>682</y>
  </Vertex>
</ArrayOfVertex>